mtcli_pivot/__init__.py
mtcli_pivot/conf.py
mtcli_pivot/pivot.py
mtcli_pivot-0.2.1.dist-info/entry_points.txt
mtcli_pivot-0.2.1.dist-info/LICENSE
mtcli_pivot-0.2.1.dist-info/METADATA
mtcli_pivot-0.2.1.dist-info/WHEEL
mtcli_pivot-0.2.1.dist-info/RECORD
