Metadata-Version: 2.3
Name: mtcli-pivot
Version: 0.2.1
Summary: Plugin mtcli do indicador pivot point
License: GPL-3.0
Keywords: CLI,trading,mt5,pivot point,ponto pivô
Author: Valmir França da Silva
Author-email: vfranca3@gmail.com
Requires-Python: >=3.11,<3.14.0
Classifier: License :: OSI Approved :: GNU General Public License v3 (GPLv3)
Classifier: Programming Language :: Python :: 3
Classifier: Programming Language :: Python :: 3.11
Classifier: Programming Language :: Python :: 3.12
Classifier: Programming Language :: Python :: 3.13
Requires-Dist: mtcli (>=1.18.1)
Project-URL: Documentation, https://vfranca.github.io/mtcli-pivot
Project-URL: Homepage, https://github.com/vfranca/mtcli-pivot
Project-URL: Repository, https://github.com/vfranca/mtcli-pivot
Project-URL: issues, https://github.com/vfranca/mtcli-pivot/issues
